odoo/addons/account_invoice_fixed_discount/README.rst
odoo/addons/account_invoice_fixed_discount/__init__.py
odoo/addons/account_invoice_fixed_discount/__manifest__.py
odoo/addons/account_invoice_fixed_discount/i18n/account_invoice_fixed_discount.pot
odoo/addons/account_invoice_fixed_discount/i18n/ca.po
odoo/addons/account_invoice_fixed_discount/i18n/de.po
odoo/addons/account_invoice_fixed_discount/i18n/es.po
odoo/addons/account_invoice_fixed_discount/i18n/fr.po
odoo/addons/account_invoice_fixed_discount/i18n/it.po
odoo/addons/account_invoice_fixed_discount/i18n/pt_BR.po
odoo/addons/account_invoice_fixed_discount/models/__init__.py
odoo/addons/account_invoice_fixed_discount/models/account_move_line.py
odoo/addons/account_invoice_fixed_discount/models/account_tax.py
odoo/addons/account_invoice_fixed_discount/readme/CONTRIBUTORS.md
odoo/addons/account_invoice_fixed_discount/readme/DESCRIPTION.md
odoo/addons/account_invoice_fixed_discount/readme/INSTALL.md
odoo/addons/account_invoice_fixed_discount/readme/USAGE.md
odoo/addons/account_invoice_fixed_discount/reports/report_account_invoice.xml
odoo/addons/account_invoice_fixed_discount/security/res_groups.xml
odoo/addons/account_invoice_fixed_discount/static/description/icon.png
odoo/addons/account_invoice_fixed_discount/static/description/index.html
odoo/addons/account_invoice_fixed_discount/tests/__init__.py
odoo/addons/account_invoice_fixed_discount/tests/test_account_fixed_discount.py
odoo/addons/account_invoice_fixed_discount/views/account_move_view.xml
odoo_addon_account_invoice_fixed_discount-19.0.1.0.0.2.dist-info/METADATA
odoo_addon_account_invoice_fixed_discount-19.0.1.0.0.2.dist-info/WHEEL
odoo_addon_account_invoice_fixed_discount-19.0.1.0.0.2.dist-info/top_level.txt
odoo_addon_account_invoice_fixed_discount-19.0.1.0.0.2.dist-info/RECORD
