Metadata-Version: 2.1
Name: odoo-addon-account_invoice_fixed_discount
Version: 19.0.1.0.0.2
Requires-Dist: odoo==19.0.*
Summary: Allows to apply fixed amount discounts in invoices.
Home-page: https://github.com/OCA/account-invoicing
License: AGPL-3
Author: ForgeFlow, Odoo Community Association (OCA)
Author-email: support@odoo-community.org
Classifier: Programming Language :: Python
Classifier: Framework :: Odoo
Classifier: Framework :: Odoo :: 19.0
Classifier: License :: OSI Approved :: GNU Affero General Public License v3
